lplug/__init__.py
lplug/manager.py
lplug-0.1.0.dist-info/LICENSE
lplug-0.1.0.dist-info/METADATA
lplug-0.1.0.dist-info/WHEEL
lplug-0.1.0.dist-info/top_level.txt
lplug-0.1.0.dist-info/RECORD
