Metadata-Version: 2.1
Name: lplug
Version: 0.1.0
Summary: Flexible and dynamic plugin system
Home-page: https://gitlab.com/prettyetc/lplug
Author: trollodel
License: UNKNOWN
Project-URL: Bug Reports, https://gitlab.com/prettyetc/lplug/issues
Project-URL: Documentation, https://prettyetc.gitlab.io/lplug/
Project-URL: Source, https://gitlab.com/prettyetc/lplug
Keywords: plugin plug-in modules setuptools entry_point yapsy
Platform: UNKNOWN
Classifier: Development Status :: 5 - Production/Stable
Classifier: License :: OSI Approved :: GNU General Public License v3 (GPLv3)
Classifier: Programming Language :: Python :: 3
Classifier: Programming Language :: Python :: 3.4
Classifier: Programming Language :: Python :: 3.5
Classifier: Programming Language :: Python :: 3.6
Classifier: Programming Language :: Python :: 3.7
Classifier: Programming Language :: Python :: 3.8
Classifier: Programming Language :: Python :: 3 :: Only
Classifier: Operating System :: OS Independent
Classifier: Topic :: Documentation :: Sphinx
Classifier: Intended Audience :: Developers
Requires-Python: >=3.4, <4
Requires-Dist: setuptools
Provides-Extra: test
Requires-Dist: pytest ; extra == 'test'
Requires-Dist: hypothesis ; extra == 'test'
